{\"0\": [{ \"xAxis\": \"true\", \"yAxis\":41.4021164021164},{ \"xAxis\": \"false\", \"yAxis\":58.597883597883595},{\"childrenIndex\":[1, 2, 3, 4, 5], \"populationSize\":756.0, \"filter\":\"#\",\"yName\":\"% of passengers\",\"xName\":\"survived\"}],\"1\": [{ \"xAxis\": \"true\", \"yAxis\":75.34722222222221},{ \"xAxis\": \"false\", \"yAxis\":24.65277777777778},{\"childrenIndex\":[6, 7], \"populationSize\":288.0, \"filter\":\"#gender$female#\",\"yName\":\"% of passengers\",\"xName\":\"survived\"}],\"3\": [{ \"xAxis\": \"true\", \"yAxis\":61.504424778761056},{ \"xAxis\": \"false\", \"yAxis\":38.49557522123894},{\"childrenIndex\":[9], \"populationSize\":226.0, \"filter\":\"#pc_class$1#\",\"yName\":\"% of passengers\",\"xName\":\"survived\"}],\"6\": [{ \"xAxis\": \"true\", \"yAxis\":95.04950495049505},{ \"xAxis\": \"false\", \"yAxis\":4.9504950495049505},{\"childrenIndex\":[], \"populationSize\":101.0, \"filter\":\"#gender$female#pc_class$1#\",\"yName\":\"% of passengers\",\"xName\":\"survived\"}],\"9\": [{ \"xAxis\": \"true\", \"yAxis\":34.4},{ \"xAxis\": \"false\", \"yAxis\":65.60000000000001},{\"childrenIndex\":[], \"populationSize\":125.0, \"filter\":\"#gender$male#pc_class$1#\",\"yName\":\"% of passengers\",\"xName\":\"survived\"}],\"7\": [{ \"xAxis\": \"true\", \"yAxis\":88.23529411764706},{ \"xAxis\": \"false\", \"yAxis\":11.76470588235294},{\"childrenIndex\":[], \"populationSize\":85.0, \"filter\":\"#gender$female#pc_class$2#\",\"yName\":\"% of passengers\",\"xName\":\"survived\"}],\"5\": [{ \"xAxis\": \"true\", \"yAxis\":24.528301886792452},{ \"xAxis\": \"false\", \"yAxis\":75.47169811320755},{\"childrenIndex\":[8], \"populationSize\":318.0, \"filter\":\"#pc_class$3#\",\"yName\":\"% of passengers\",\"xName\":\"survived\"}],\"8\": [{ \"xAxis\": \"true\", \"yAxis\":45.09803921568628},{ \"xAxis\": \"false\", \"yAxis\":54.90196078431373},{\"childrenIndex\":[], \"populationSize\":102.0, \"filter\":\"#gender$female#pc_class$3#\",\"yName\":\"% of passengers\",\"xName\":\"survived\"}],\"2\": [{ \"xAxis\": \"true\", \"yAxis\":20.51282051282051},{ \"xAxis\": \"false\", \"yAxis\":79.48717948717949},{\"childrenIndex\":[9, 10, 11], \"populationSize\":468.0, \"filter\":\"#gender$male#\",\"yName\":\"% of passengers\",\"xName\":\"survived\"}],\"10\": [{ \"xAxis\": \"true\", \"yAxis\":16.535433070866144},{ \"xAxis\": \"false\", \"yAxis\":83.46456692913385},{\"childrenIndex\":[], \"populationSize\":127.0, \"filter\":\"#gender$male#pc_class$2#\",\"yName\":\"% of passengers\",\"xName\":\"survived\"}]}